<?xml version="1.0" encoding="utf-8"?>
<clothing-items>
 <clothing>
  <id>
   268550796
  </id>
  <name>
   Nike Jeans B-1076
  </name>
  <category>
   Jeans
  </category>
  <size>
   M
  </size>
  <color>
   Оранжевый
  </color>
  <material>
   Шелк
  </material>
  <price>
   482983
  </price>
  <rating>
   3.07
  </rating>
  <reviews>
   614254
  </reviews>
  <sporty>
   yes
  </sporty>
 </clothing>
 <clothing>
  <id>
   510613195
  </id>
  <name>
   Ellesse Shirt T-9535
  </name>
  <category>
   Shirt
  </category>
  <size>
   XXL
  </size>
  <color>
   Синий
  </color>
  <material>
   Шелк
  </material>
  <price>
   639998
  </price>
  <rating>
   4.46
  </rating>
  <reviews>
   619945
  </reviews>
  <new>
   -
  </new>
  <exclusive>
   yes
  </exclusive>
  <sporty>
   no
  </sporty>
 </clothing>
 <clothing>
  <id>
   276295534
  </id>
  <name>
   Asics Pants K-6914
  </name>
  <category>
   Pants
  </category>
  <size>
   M
  </size>
  <color>
   Фиолетовый
  </color>
  <material>
   Нейлон
  </material>
  <price>
   545506
  </price>
  <rating>
   2.23
  </rating>
  <reviews>
   423835
  </reviews>
  <new>
   -
  </new>
  <exclusive>
   no
  </exclusive>
 </clothing>
 <clothing>
  <id>
   437338626
  </id>
  <name>
   Brooks T-shirt G-3545
  </name>
  <category>
   T-shirt
  </category>
  <size>
   L
  </size>
  <color>
   Оранжевый
  </color>
  <material>
   Лен
  </material>
  <price>
   667779
  </price>
  <rating>
   3.3
  </rating>
  <reviews>
   944488
  </reviews>
  <new>
   -
  </new>
  <exclusive>
   no
  </exclusive>
 </clothing>
 <clothing>
  <id>
   266414839
  </id>
  <name>
   Nike Skirt U-8136
  </name>
  <category>
   Skirt
  </category>
  <size>
   XL
  </size>
  <color>
   Голубой
  </color>
  <material>
   Шелк
  </material>
  <price>
   435051
  </price>
  <rating>
   2.42
  </rating>
  <reviews>
   625762
  </reviews>
  <new>
   -
  </new>
  <exclusive>
   no
  </exclusive>
  <sporty>
   no
  </sporty>
 </clothing>
 <clothing>
  <id>
   331153922
  </id>
  <name>
   New Balance Umbrellas F-7889
  </name>
  <category>
   Umbrellas
  </category>
  <size>
   S
  </size>
  <color>
   Голубой
  </color>
  <material>
   Полиэстер
  </material>
  <price>
   127097
  </price>
  <rating>
   1.34
  </rating>
  <reviews>
   140460
  </reviews>
  <new>
   +
  </new>
 </clothing>
 <clothing>
  <id>
   463194805
  </id>
  <name>
   New Balance Pants Z-5525
  </name>
  <category>
   Pants
  </category>
  <size>
   XL
  </size>
  <color>
   Оранжевый
  </color>
  <material>
   Кожа
  </material>
  <price>
   124506
  </price>
  <rating>
   2.18
  </rating>
  <reviews>
   372330
  </reviews>
  <new>
   -
  </new>
  <exclusive>
   yes
  </exclusive>
 </clothing>
 <clothing>
  <id>
   411394153
  </id>
  <name>
   Vans Jacket Q-4248
  </name>
  <category>
   Jacket
  </category>
  <size>
   L
  </size>
  <color>
   Голубой
  </color>
  <material>
   Хлопок
  </material>
  <price>
   608798
  </price>
  <rating>
   1.37
  </rating>
  <reviews>
   59530
  </reviews>
  <new>
   +
  </new>
 </clothing>
 <clothing>
  <id>
   526736814
  </id>
  <name>
   DC Umbrellas D-6017
  </name>
  <category>
   Umbrellas
  </category>
  <size>
   XXL
  </size>
  <color>
   Синий
  </color>
  <material>
   Лен
  </material>
  <price>
   369026
  </price>
  <rating>
   4.06
  </rating>
  <reviews>
   417328
  </reviews>
  <new>
   -
  </new>
  <sporty>
   no
  </sporty>
 </clothing>
 <clothing>
  <id>
   528179216
  </id>
  <name>
   Ellesse Gloves Y-3677
  </name>
  <category>
   Gloves
  </category>
  <size>
   XXL
  </size>
  <color>
   Желтый
  </color>
  <material>
   Хлопок
  </material>
  <price>
   504359
  </price>
  <rating>
   3.86
  </rating>
  <reviews>
   470790
  </reviews>
  <new>
   -
  </new>
  <exclusive>
   yes
  </exclusive>
  <sporty>
   yes
  </sporty>
 </clothing>
 <clothing>
  <id>
   994296243
  </id>
  <name>
   Puma Belts B-7398
  </name>
  <category>
   Belts
  </category>
  <size>
   L
  </size>
  <color>
   Зеленый
  </color>
  <material>
   Нейлон
  </material>
  <price>
   156758
  </price>
  <rating>
   1.96
  </rating>
  <reviews>
   607191
  </reviews>
  <new>
   +
  </new>
  <exclusive>
   yes
  </exclusive>
 </clothing>
 <clothing>
  <id>
   237741077
  </id>
  <name>
   Vans Blouse G-8695
  </name>
  <category>
   Blouse
  </category>
  <size>
   M
  </size>
  <color>
   Голубой
  </color>
  <material>
   Хлопок
  </material>
  <price>
   877999
  </price>
  <rating>
   2.17
  </rating>
  <reviews>
   146281
  </reviews>
  <new>
   -
  </new>
  <exclusive>
   no
  </exclusive>
  <sporty>
   no
  </sporty>
 </clothing>
 <clothing>
  <id>
   161011818
  </id>
  <name>
   Converse Jeans V-1617
  </name>
  <category>
   Jeans
  </category>
  <size>
   XXL
  </size>
  <color>
   Зеленый
  </color>
  <material>
   Полиэстер
  </material>
  <price>
   288573
  </price>
  <rating>
   2.48
  </rating>
  <reviews>
   707420
  </reviews>
 </clothing>
 <clothing>
  <id>
   697547846
  </id>
  <name>
   PleinSport T-shirt W-4794
  </name>
  <category>
   T-shirt
  </category>
  <size>
   S
  </size>
  <color>
   Красный
  </color>
  <material>
   Кожа
  </material>
  <price>
   351293
  </price>
  <rating>
   2.88
  </rating>
  <reviews>
   633179
  </reviews>
  <sporty>
   no
  </sporty>
 </clothing>
 <clothing>
  <id>
   903347931
  </id>
  <name>
   Under Armour Handbags Q-9676
  </name>
  <category>
   Handbags
  </category>
  <size>
   XXL
  </size>
  <color>
   Фиолетовый
  </color>
  <material>
   Шерсть
  </material>
  <price>
   193908
  </price>
  <rating>
   3.33
  </rating>
  <reviews>
   232524
  </reviews>
  <new>
   +
  </new>
  <exclusive>
   yes
  </exclusive>
  <sporty>
   no
  </sporty>
 </clothing>
 <clothing>
  <id>
   979321092
  </id>
  <name>
   DC Jeans Y-8391
  </name>
  <category>
   Jeans
  </category>
  <size>
   S
  </size>
  <color>
   Фиолетовый
  </color>
  <material>
   Шерсть
  </material>
  <price>
   126026
  </price>
  <rating>
   3.24
  </rating>
  <reviews>
   8697
  </reviews>
  <exclusive>
   no
  </exclusive>
  <sporty>
   yes
  </sporty>
 </clothing>
 <clothing>
  <id>
   876038913
  </id>
  <name>
   PleinSport T-shirt X-6283
  </name>
  <category>
   T-shirt
  </category>
  <size>
   L
  </size>
  <color>
   Голубой
  </color>
  <material>
   Лен
  </material>
  <price>
   552021
  </price>
  <rating>
   2.66
  </rating>
  <reviews>
   198883
  </reviews>
  <exclusive>
   no
  </exclusive>
 </clothing>
 <clothing>
  <id>
   567080770
  </id>
  <name>
   Fila Shirt C-9380
  </name>
  <category>
   Shirt
  </category>
  <size>
   XL
  </size>
  <color>
   Синий
  </color>
  <material>
   Вискоза
  </material>
  <price>
   626240
  </price>
  <rating>
   2.39
  </rating>
  <reviews>
   560959
  </reviews>
  <new>
   +
  </new>
  <exclusive>
   yes
  </exclusive>
 </clothing>
 <clothing>
  <id>
   817362855
  </id>
  <name>
   Fila Skirt H-1216
  </name>
  <category>
   Skirt
  </category>
  <size>
   L
  </size>
  <color>
   Синий
  </color>
  <material>
   Хлопок
  </material>
  <price>
   395545
  </price>
  <rating>
   3.57
  </rating>
  <reviews>
   446873
  </reviews>
  <new>
   -
  </new>
  <exclusive>
   no
  </exclusive>
  <sporty>
   no
  </sporty>
 </clothing>
 <clothing>
  <id>
   922430948
  </id>
  <name>
   DC Hat P-8364
  </name>
  <category>
   Hat
  </category>
  <size>
   XL
  </size>
  <color>
   Фиолетовый
  </color>
  <material>
   Хлопок
  </material>
  <price>
   864338
  </price>
  <rating>
   2.68
  </rating>
  <reviews>
   343058
  </reviews>
  <new>
   -
  </new>
  <exclusive>
   no
  </exclusive>
  <sporty>
   yes
  </sporty>
 </clothing>
 <clothing>
  <id>
   377808667
  </id>
  <name>
   Adidas Gloves O-1017
  </name>
  <category>
   Gloves
  </category>
  <size>
   S
  </size>
  <color>
   Фиолетовый
  </color>
  <material>
   Полиэстер
  </material>
  <price>
   956268
  </price>
  <rating>
   3.76
  </rating>
  <reviews>
   4358
  </reviews>
  <new>
   -
  </new>
  <exclusive>
   yes
  </exclusive>
 </clothing>
 <clothing>
  <id>
   692571669
  </id>
  <name>
   Asics Blouse Q-9937
  </name>
  <category>
   Blouse
  </category>
  <size>
   XL
  </size>
  <color>
   Зеленый
  </color>
  <material>
   Хлопок
  </material>
  <price>
   348401
  </price>
  <rating>
   4.7
  </rating>
  <reviews>
   64224
  </reviews>
  <new>
   +
  </new>
  <exclusive>
   no
  </exclusive>
 </clothing>
 <clothing>
  <id>
   574710305
  </id>
  <name>
   DC Handbags T-7740
  </name>
  <category>
   Handbags
  </category>
  <size>
   M
  </size>
  <color>
   Фиолетовый
  </color>
  <material>
   Хлопок
  </material>
  <price>
   699498
  </price>
  <rating>
   4.57
  </rating>
  <reviews>
   714975
  </reviews>
  <new>
   -
  </new>
  <exclusive>
   yes
  </exclusive>
  <sporty>
   yes
  </sporty>
 </clothing>
 <clothing>
  <id>
   181162676
  </id>
  <name>
   Fila Gloves M-3496
  </name>
  <category>
   Gloves
  </category>
  <size>
   L
  </size>
  <color>
   Фиолетовый
  </color>
  <material>
   Хлопок
  </material>
  <price>
   764084
  </price>
  <rating>
   3.69
  </rating>
  <reviews>
   865081
  </reviews>
  <new>
   +
  </new>
 </clothing>
 <clothing>
  <id>
   368175609
  </id>
  <name>
   Nike Skirt X-2347
  </name>
  <category>
   Skirt
  </category>
  <size>
   XL
  </size>
  <color>
   Голубой
  </color>
  <material>
   Кожа
  </material>
  <price>
   654140
  </price>
  <rating>
   1.18
  </rating>
  <reviews>
   294441
  </reviews>
  <sporty>
   no
  </sporty>
 </clothing>
 <clothing>
  <id>
   396847372
  </id>
  <name>
   Vans Belts F-2297
  </name>
  <category>
   Belts
  </category>
  <size>
   M
  </size>
  <color>
   Зеленый
  </color>
  <material>
   Лен
  </material>
  <price>
   589479
  </price>
  <rating>
   2.25
  </rating>
  <reviews>
   447576
  </reviews>
  <sporty>
   no
  </sporty>
 </clothing>
</clothing-items>
