<?xml version="1.0" encoding="utf-8"?>
<clothing-items>
 <clothing>
  <id>
   557648208
  </id>
  <name>
   Vans Dress T-3303
  </name>
  <category>
   Dress
  </category>
  <size>
   XXL
  </size>
  <color>
   Фиолетовый
  </color>
  <material>
   Вискоза
  </material>
  <price>
   956539
  </price>
  <rating>
   3.83
  </rating>
  <reviews>
   783790
  </reviews>
 </clothing>
 <clothing>
  <id>
   811266444
  </id>
  <name>
   New Balance Blouse Y-1322
  </name>
  <category>
   Blouse
  </category>
  <size>
   XL
  </size>
  <color>
   Зеленый
  </color>
  <material>
   Шелк
  </material>
  <price>
   877840
  </price>
  <rating>
   1.09
  </rating>
  <reviews>
   324183
  </reviews>
  <exclusive>
   no
  </exclusive>
 </clothing>
 <clothing>
  <id>
   875791782
  </id>
  <name>
   DC Jacket A-6200
  </name>
  <category>
   Jacket
  </category>
  <size>
   M
  </size>
  <color>
   Оранжевый
  </color>
  <material>
   Шелк
  </material>
  <price>
   555154
  </price>
  <rating>
   3.7
  </rating>
  <reviews>
   148859
  </reviews>
  <exclusive>
   no
  </exclusive>
  <sporty>
   yes
  </sporty>
 </clothing>
 <clothing>
  <id>
   155097008
  </id>
  <name>
   Reebok Pants U-6116
  </name>
  <category>
   Pants
  </category>
  <size>
   XXL
  </size>
  <color>
   Синий
  </color>
  <material>
   Полиэстер
  </material>
  <price>
   303664
  </price>
  <rating>
   2.19
  </rating>
  <reviews>
   80731
  </reviews>
  <new>
   -
  </new>
  <sporty>
   no
  </sporty>
 </clothing>
 <clothing>
  <id>
   172272594
  </id>
  <name>
   Fila Sweater U-8640
  </name>
  <category>
   Sweater
  </category>
  <size>
   L
  </size>
  <color>
   Синий
  </color>
  <material>
   Хлопок
  </material>
  <price>
   107004
  </price>
  <rating>
   3.22
  </rating>
  <reviews>
   523413
  </reviews>
  <new>
   +
  </new>
  <exclusive>
   no
  </exclusive>
  <sporty>
   no
  </sporty>
 </clothing>
 <clothing>
  <id>
   361188974
  </id>
  <name>
   PleinSport Umbrellas M-5828
  </name>
  <category>
   Umbrellas
  </category>
  <size>
   M
  </size>
  <color>
   Голубой
  </color>
  <material>
   Шерсть
  </material>
  <price>
   899435
  </price>
  <rating>
   2.17
  </rating>
  <reviews>
   929812
  </reviews>
  <new>
   +
  </new>
  <exclusive>
   no
  </exclusive>
 </clothing>
 <clothing>
  <id>
   849718896
  </id>
  <name>
   Adidas Handbags J-3838
  </name>
  <category>
   Handbags
  </category>
  <size>
   XXL
  </size>
  <color>
   Голубой
  </color>
  <material>
   Вискоза
  </material>
  <price>
   755769
  </price>
  <rating>
   4.86
  </rating>
  <reviews>
   610233
  </reviews>
  <new>
   +
  </new>
  <exclusive>
   no
  </exclusive>
  <sporty>
   no
  </sporty>
 </clothing>
 <clothing>
  <id>
   419069168
  </id>
  <name>
   Under Armour Umbrellas D-8565
  </name>
  <category>
   Umbrellas
  </category>
  <size>
   M
  </size>
  <color>
   Синий
  </color>
  <material>
   Полиэстер
  </material>
  <price>
   579646
  </price>
  <rating>
   1.94
  </rating>
  <reviews>
   289554
  </reviews>
  <new>
   +
  </new>
  <exclusive>
   no
  </exclusive>
  <sporty>
   no
  </sporty>
 </clothing>
 <clothing>
  <id>
   684293373
  </id>
  <name>
   Addidas Hat Y-3614
  </name>
  <category>
   Hat
  </category>
  <size>
   XL
  </size>
  <color>
   Красный
  </color>
  <material>
   Шерсть
  </material>
  <price>
   102927
  </price>
  <rating>
   3.77
  </rating>
  <reviews>
   812526
  </reviews>
  <new>
   +
  </new>
  <exclusive>
   no
  </exclusive>
  <sporty>
   yes
  </sporty>
 </clothing>
 <clothing>
  <id>
   877506689
  </id>
  <name>
   Puma Socks I-5007
  </name>
  <category>
   Socks
  </category>
  <size>
   L
  </size>
  <color>
   Синий
  </color>
  <material>
   Шелк
  </material>
  <price>
   279244
  </price>
  <rating>
   3.13
  </rating>
  <reviews>
   487413
  </reviews>
  <new>
   -
  </new>
  <exclusive>
   yes
  </exclusive>
  <sporty>
   no
  </sporty>
 </clothing>
 <clothing>
  <id>
   581675121
  </id>
  <name>
   New Balance Gloves K-8331
  </name>
  <category>
   Gloves
  </category>
  <size>
   M
  </size>
  <color>
   Красный
  </color>
  <material>
   Кожа
  </material>
  <price>
   621604
  </price>
  <rating>
   3.05
  </rating>
  <reviews>
   505619
  </reviews>
  <new>
   -
  </new>
  <exclusive>
   no
  </exclusive>
  <sporty>
   yes
  </sporty>
 </clothing>
 <clothing>
  <id>
   161824936
  </id>
  <name>
   Addidas Socks E-4971
  </name>
  <category>
   Socks
  </category>
  <size>
   XXL
  </size>
  <color>
   Красный
  </color>
  <material>
   Полиэстер
  </material>
  <price>
   834935
  </price>
  <rating>
   2.93
  </rating>
  <reviews>
   149270
  </reviews>
  <new>
   +
  </new>
  <exclusive>
   no
  </exclusive>
  <sporty>
   yes
  </sporty>
 </clothing>
 <clothing>
  <id>
   732030962
  </id>
  <name>
   Reebok T-shirt K-8461
  </name>
  <category>
   T-shirt
  </category>
  <size>
   XXL
  </size>
  <color>
   Синий
  </color>
  <material>
   Шерсть
  </material>
  <price>
   696816
  </price>
  <rating>
   2.27
  </rating>
  <reviews>
   205328
  </reviews>
  <new>
   -
  </new>
  <sporty>
   no
  </sporty>
 </clothing>
 <clothing>
  <id>
   361268152
  </id>
  <name>
   DC Sweater G-3075
  </name>
  <category>
   Sweater
  </category>
  <size>
   XXL
  </size>
  <color>
   Зеленый
  </color>
  <material>
   Шерсть
  </material>
  <price>
   999137
  </price>
  <rating>
   2.3
  </rating>
  <reviews>
   32616
  </reviews>
  <exclusive>
   yes
  </exclusive>
 </clothing>
 <clothing>
  <id>
   801896339
  </id>
  <name>
   Converse Belts A-6034
  </name>
  <category>
   Belts
  </category>
  <size>
   M
  </size>
  <color>
   Фиолетовый
  </color>
  <material>
   Кожа
  </material>
  <price>
   500680
  </price>
  <rating>
   4.24
  </rating>
  <reviews>
   75683
  </reviews>
  <new>
   -
  </new>
  <exclusive>
   yes
  </exclusive>
 </clothing>
 <clothing>
  <id>
   444734490
  </id>
  <name>
   PleinSport Shirt O-7934
  </name>
  <category>
   Shirt
  </category>
  <size>
   XL
  </size>
  <color>
   Синий
  </color>
  <material>
   Шерсть
  </material>
  <price>
   303076
  </price>
  <rating>
   3.24
  </rating>
  <reviews>
   274864
  </reviews>
  <new>
   -
  </new>
  <exclusive>
   no
  </exclusive>
  <sporty>
   no
  </sporty>
 </clothing>
 <clothing>
  <id>
   896518076
  </id>
  <name>
   Converse Belts F-5874
  </name>
  <category>
   Belts
  </category>
  <size>
   XXL
  </size>
  <color>
   Зеленый
  </color>
  <material>
   Полиэстер
  </material>
  <price>
   282171
  </price>
  <rating>
   4.8
  </rating>
  <reviews>
   814264
  </reviews>
  <new>
   +
  </new>
  <exclusive>
   yes
  </exclusive>
 </clothing>
 <clothing>
  <id>
   755463209
  </id>
  <name>
   Ellesse Dress N-8652
  </name>
  <category>
   Dress
  </category>
  <size>
   S
  </size>
  <color>
   Оранжевый
  </color>
  <material>
   Хлопок
  </material>
  <price>
   818036
  </price>
  <rating>
   4.72
  </rating>
  <reviews>
   53159
  </reviews>
  <new>
   -
  </new>
  <exclusive>
   yes
  </exclusive>
 </clothing>
 <clothing>
  <id>
   161831523
  </id>
  <name>
   Vans Shoes I-5492
  </name>
  <category>
   Shoes
  </category>
  <size>
   S
  </size>
  <color>
   Голубой
  </color>
  <material>
   Полиэстер
  </material>
  <price>
   234663
  </price>
  <rating>
   1.75
  </rating>
  <reviews>
   727824
  </reviews>
  <exclusive>
   no
  </exclusive>
 </clothing>
 <clothing>
  <id>
   146717052
  </id>
  <name>
   Under Armour Pants E-1270
  </name>
  <category>
   Pants
  </category>
  <size>
   XL
  </size>
  <color>
   Зеленый
  </color>
  <material>
   Хлопок
  </material>
  <price>
   666851
  </price>
  <rating>
   3.47
  </rating>
  <reviews>
   638137
  </reviews>
  <exclusive>
   no
  </exclusive>
  <sporty>
   yes
  </sporty>
 </clothing>
 <clothing>
  <id>
   554415736
  </id>
  <name>
   Reebok Jacket K-5175
  </name>
  <category>
   Jacket
  </category>
  <size>
   M
  </size>
  <color>
   Фиолетовый
  </color>
  <material>
   Вискоза
  </material>
  <price>
   257914
  </price>
  <rating>
   4.86
  </rating>
  <reviews>
   257823
  </reviews>
  <new>
   +
  </new>
  <exclusive>
   no
  </exclusive>
  <sporty>
   no
  </sporty>
 </clothing>
 <clothing>
  <id>
   549047423
  </id>
  <name>
   PleinSport Umbrellas N-5108
  </name>
  <category>
   Umbrellas
  </category>
  <size>
   XXL
  </size>
  <color>
   Желтый
  </color>
  <material>
   Лен
  </material>
  <price>
   217566
  </price>
  <rating>
   4.1
  </rating>
  <reviews>
   199744
  </reviews>
 </clothing>
 <clothing>
  <id>
   902346494
  </id>
  <name>
   Reebok Umbrellas N-8481
  </name>
  <category>
   Umbrellas
  </category>
  <size>
   M
  </size>
  <color>
   Фиолетовый
  </color>
  <material>
   Вискоза
  </material>
  <price>
   420151
  </price>
  <rating>
   4.3
  </rating>
  <reviews>
   965453
  </reviews>
  <new>
   -
  </new>
  <exclusive>
   no
  </exclusive>
  <sporty>
   yes
  </sporty>
 </clothing>
 <clothing>
  <id>
   942864255
  </id>
  <name>
   Reebok Skirt O-5001
  </name>
  <category>
   Skirt
  </category>
  <size>
   XL
  </size>
  <color>
   Оранжевый
  </color>
  <material>
   Лен
  </material>
  <price>
   237683
  </price>
  <rating>
   3.48
  </rating>
  <reviews>
   701313
  </reviews>
  <exclusive>
   yes
  </exclusive>
 </clothing>
 <clothing>
  <id>
   151447769
  </id>
  <name>
   Nike Gloves U-2135
  </name>
  <category>
   Gloves
  </category>
  <size>
   L
  </size>
  <color>
   Красный
  </color>
  <material>
   Шерсть
  </material>
  <price>
   902513
  </price>
  <rating>
   4.97
  </rating>
  <reviews>
   663133
  </reviews>
  <exclusive>
   no
  </exclusive>
  <sporty>
   no
  </sporty>
 </clothing>
 <clothing>
  <id>
   884292526
  </id>
  <name>
   Lacoste Pants U-2817
  </name>
  <category>
   Pants
  </category>
  <size>
   M
  </size>
  <color>
   Голубой
  </color>
  <material>
   Шелк
  </material>
  <price>
   671325
  </price>
  <rating>
   1.15
  </rating>
  <reviews>
   241232
  </reviews>
  <new>
   -
  </new>
 </clothing>
 <clothing>
  <id>
   285091055
  </id>
  <name>
   New Balance Jeans K-2723
  </name>
  <category>
   Jeans
  </category>
  <size>
   XL
  </size>
  <color>
   Голубой
  </color>
  <material>
   Лен
  </material>
  <price>
   573692
  </price>
  <rating>
   3.75
  </rating>
  <reviews>
   635881
  </reviews>
  <new>
   -
  </new>
 </clothing>
 <clothing>
  <id>
   225583727
  </id>
  <name>
   Under Armour Sweater C-2790
  </name>
  <category>
   Sweater
  </category>
  <size>
   M
  </size>
  <color>
   Синий
  </color>
  <material>
   Кожа
  </material>
  <price>
   301975
  </price>
  <rating>
   3.91
  </rating>
  <reviews>
   986439
  </reviews>
  <new>
   -
  </new>
  <sporty>
   no
  </sporty>
 </clothing>
 <clothing>
  <id>
   480677444
  </id>
  <name>
   New Balance Gloves R-6826
  </name>
  <category>
   Gloves
  </category>
  <size>
   XXL
  </size>
  <color>
   Фиолетовый
  </color>
  <material>
   Шелк
  </material>
  <price>
   266417
  </price>
  <rating>
   3.4
  </rating>
  <reviews>
   503122
  </reviews>
  <new>
   +
  </new>
  <exclusive>
   no
  </exclusive>
 </clothing>
 <clothing>
  <id>
   244296431
  </id>
  <name>
   DC Jeans Q-8188
  </name>
  <category>
   Jeans
  </category>
  <size>
   S
  </size>
  <color>
   Фиолетовый
  </color>
  <material>
   Вискоза
  </material>
  <price>
   182728
  </price>
  <rating>
   1.16
  </rating>
  <reviews>
   127720
  </reviews>
  <new>
   +
  </new>
  <exclusive>
   no
  </exclusive>
  <sporty>
   yes
  </sporty>
 </clothing>
 <clothing>
  <id>
   666854416
  </id>
  <name>
   Ellesse Shoes E-4769
  </name>
  <category>
   Shoes
  </category>
  <size>
   S
  </size>
  <color>
   Фиолетовый
  </color>
  <material>
   Хлопок
  </material>
  <price>
   803463
  </price>
  <rating>
   1.78
  </rating>
  <reviews>
   506112
  </reviews>
  <exclusive>
   yes
  </exclusive>
  <sporty>
   yes
  </sporty>
 </clothing>
 <clothing>
  <id>
   965986008
  </id>
  <name>
   Reebok Dress C-2521
  </name>
  <category>
   Dress
  </category>
  <size>
   M
  </size>
  <color>
   Оранжевый
  </color>
  <material>
   Лен
  </material>
  <price>
   493086
  </price>
  <rating>
   4.99
  </rating>
  <reviews>
   550654
  </reviews>
  <new>
   -
  </new>
 </clothing>
 <clothing>
  <id>
   968522173
  </id>
  <name>
   New Balance Socks O-9006
  </name>
  <category>
   Socks
  </category>
  <size>
   L
  </size>
  <color>
   Зеленый
  </color>
  <material>
   Лен
  </material>
  <price>
   862981
  </price>
  <rating>
   1.93
  </rating>
  <reviews>
   42350
  </reviews>
  <new>
   -
  </new>
  <exclusive>
   yes
  </exclusive>
  <sporty>
   no
  </sporty>
 </clothing>
 <clothing>
  <id>
   629513792
  </id>
  <name>
   Brooks Gloves J-4667
  </name>
  <category>
   Gloves
  </category>
  <size>
   L
  </size>
  <color>
   Синий
  </color>
  <material>
   Шелк
  </material>
  <price>
   843405
  </price>
  <rating>
   2.68
  </rating>
  <reviews>
   417180
  </reviews>
  <new>
   -
  </new>
  <sporty>
   no
  </sporty>
 </clothing>
 <clothing>
  <id>
   895755755
  </id>
  <name>
   Vans Shoes F-5111
  </name>
  <category>
   Shoes
  </category>
  <size>
   XL
  </size>
  <color>
   Зеленый
  </color>
  <material>
   Вискоза
  </material>
  <price>
   711974
  </price>
  <rating>
   4.14
  </rating>
  <reviews>
   658213
  </reviews>
  <exclusive>
   no
  </exclusive>
 </clothing>
 <clothing>
  <id>
   559587357
  </id>
  <name>
   Vans Pants H-4825
  </name>
  <category>
   Pants
  </category>
  <size>
   XL
  </size>
  <color>
   Синий
  </color>
  <material>
   Шерсть
  </material>
  <price>
   681450
  </price>
  <rating>
   1.29
  </rating>
  <reviews>
   62135
  </reviews>
  <new>
   -
  </new>
  <sporty>
   no
  </sporty>
 </clothing>
</clothing-items>
