<?xml version="1.0" encoding="utf-8"?>
<clothing-items>
 <clothing>
  <id>
   284129204
  </id>
  <name>
   Fila Sweater M-2593
  </name>
  <category>
   Sweater
  </category>
  <size>
   L
  </size>
  <color>
   Оранжевый
  </color>
  <material>
   Полиэстер
  </material>
  <price>
   649988
  </price>
  <rating>
   3.4
  </rating>
  <reviews>
   994103
  </reviews>
  <new>
   +
  </new>
  <exclusive>
   yes
  </exclusive>
  <sporty>
   no
  </sporty>
 </clothing>
 <clothing>
  <id>
   516004678
  </id>
  <name>
   New Balance Umbrellas J-3015
  </name>
  <category>
   Umbrellas
  </category>
  <size>
   S
  </size>
  <color>
   Синий
  </color>
  <material>
   Кожа
  </material>
  <price>
   753603
  </price>
  <rating>
   1.47
  </rating>
  <reviews>
   863233
  </reviews>
  <new>
   +
  </new>
  <exclusive>
   no
  </exclusive>
  <sporty>
   no
  </sporty>
 </clothing>
 <clothing>
  <id>
   128878038
  </id>
  <name>
   PleinSport Jeans C-1732
  </name>
  <category>
   Jeans
  </category>
  <size>
   XL
  </size>
  <color>
   Желтый
  </color>
  <material>
   Хлопок
  </material>
  <price>
   467177
  </price>
  <rating>
   3.68
  </rating>
  <reviews>
   242768
  </reviews>
  <sporty>
   no
  </sporty>
 </clothing>
 <clothing>
  <id>
   529572705
  </id>
  <name>
   Fila Dress K-6590
  </name>
  <category>
   Dress
  </category>
  <size>
   L
  </size>
  <color>
   Красный
  </color>
  <material>
   Нейлон
  </material>
  <price>
   576074
  </price>
  <rating>
   4.42
  </rating>
  <reviews>
   958524
  </reviews>
  <new>
   +
  </new>
  <exclusive>
   no
  </exclusive>
 </clothing>
 <clothing>
  <id>
   748530201
  </id>
  <name>
   Puma Jacket T-6358
  </name>
  <category>
   Jacket
  </category>
  <size>
   L
  </size>
  <color>
   Оранжевый
  </color>
  <material>
   Полиэстер
  </material>
  <price>
   103431
  </price>
  <rating>
   2.16
  </rating>
  <reviews>
   874824
  </reviews>
  <new>
   +
  </new>
  <sporty>
   yes
  </sporty>
 </clothing>
 <clothing>
  <id>
   596313279
  </id>
  <name>
   DC Socks Z-4916
  </name>
  <category>
   Socks
  </category>
  <size>
   M
  </size>
  <color>
   Желтый
  </color>
  <material>
   Лен
  </material>
  <price>
   459342
  </price>
  <rating>
   2.61
  </rating>
  <reviews>
   826176
  </reviews>
  <exclusive>
   no
  </exclusive>
  <sporty>
   no
  </sporty>
 </clothing>
 <clothing>
  <id>
   956621156
  </id>
  <name>
   Brooks Jacket N-9231
  </name>
  <category>
   Jacket
  </category>
  <size>
   L
  </size>
  <color>
   Желтый
  </color>
  <material>
   Кожа
  </material>
  <price>
   105635
  </price>
  <rating>
   1.24
  </rating>
  <reviews>
   496650
  </reviews>
  <new>
   -
  </new>
  <sporty>
   yes
  </sporty>
 </clothing>
 <clothing>
  <id>
   134343156
  </id>
  <name>
   Brooks T-shirt N-8321
  </name>
  <category>
   T-shirt
  </category>
  <size>
   M
  </size>
  <color>
   Оранжевый
  </color>
  <material>
   Хлопок
  </material>
  <price>
   232080
  </price>
  <rating>
   3.68
  </rating>
  <reviews>
   178583
  </reviews>
  <sporty>
   no
  </sporty>
 </clothing>
 <clothing>
  <id>
   169695044
  </id>
  <name>
   Converse Belts G-3698
  </name>
  <category>
   Belts
  </category>
  <size>
   S
  </size>
  <color>
   Желтый
  </color>
  <material>
   Шерсть
  </material>
  <price>
   392669
  </price>
  <rating>
   3.18
  </rating>
  <reviews>
   913126
  </reviews>
  <new>
   -
  </new>
  <sporty>
   no
  </sporty>
 </clothing>
 <clothing>
  <id>
   699570326
  </id>
  <name>
   Fila T-shirt N-6371
  </name>
  <category>
   T-shirt
  </category>
  <size>
   XL
  </size>
  <color>
   Красный
  </color>
  <material>
   Шерсть
  </material>
  <price>
   250773
  </price>
  <rating>
   1.63
  </rating>
  <reviews>
   600584
  </reviews>
  <new>
   +
  </new>
  <exclusive>
   yes
  </exclusive>
 </clothing>
 <clothing>
  <id>
   120208023
  </id>
  <name>
   Vans Pants M-1484
  </name>
  <category>
   Pants
  </category>
  <size>
   M
  </size>
  <color>
   Синий
  </color>
  <material>
   Лен
  </material>
  <price>
   617555
  </price>
  <rating>
   3.59
  </rating>
  <reviews>
   767052
  </reviews>
  <sporty>
   no
  </sporty>
 </clothing>
 <clothing>
  <id>
   505424777
  </id>
  <name>
   New Balance Umbrellas B-2868
  </name>
  <category>
   Umbrellas
  </category>
  <size>
   L
  </size>
  <color>
   Зеленый
  </color>
  <material>
   Полиэстер
  </material>
  <price>
   651958
  </price>
  <rating>
   2.79
  </rating>
  <reviews>
   839453
  </reviews>
  <exclusive>
   no
  </exclusive>
 </clothing>
 <clothing>
  <id>
   459502291
  </id>
  <name>
   Fila Gloves C-1906
  </name>
  <category>
   Gloves
  </category>
  <size>
   M
  </size>
  <color>
   Зеленый
  </color>
  <material>
   Шерсть
  </material>
  <price>
   374117
  </price>
  <rating>
   1.57
  </rating>
  <reviews>
   359158
  </reviews>
  <new>
   -
  </new>
  <exclusive>
   yes
  </exclusive>
 </clothing>
</clothing-items>
