[
    {
        "_id": "Сантьяго-де-Компостела",
        "max_age": "62",
        "min_age": "27",
        "avg_age": "52.142857142857146"
    },
    {
        "_id": "Камбадос",
        "max_age": "64",
        "min_age": "26",
        "avg_age": "48.3125"
    },
    {
        "_id": "Картахена",
        "max_age": "61",
        "min_age": "20",
        "avg_age": "48.07692307692308"
    },
    {
        "_id": "Алькала-де-Энарес",
        "max_age": "65",
        "min_age": "20",
        "avg_age": "48.0"
    },
    {
        "_id": "София",
        "max_age": "64",
        "min_age": "19",
        "avg_age": "47.44444444444444"
    },
    {
        "_id": "Севилья",
        "max_age": "62",
        "min_age": "26",
        "avg_age": "47.25"
    },
    {
        "_id": "Вальядолид",
        "max_age": "63",
        "min_age": "24",
        "avg_age": "47.125"
    },
    {
        "_id": "Таллин",
        "max_age": "65",
        "min_age": "29",
        "avg_age": "46.72222222222222"
    },
    {
        "_id": "Сьюдад-Реаль",
        "max_age": "62",
        "min_age": "29",
        "avg_age": "46.714285714285715"
    },
    {
        "_id": "Авилес",
        "max_age": "58",
        "min_age": "30",
        "avg_age": "46.6"
    },
    {
        "_id": "Эльче",
        "max_age": "63",
        "min_age": "21",
        "avg_age": "46.333333333333336"
    },
    {
        "_id": "Кадакес",
        "max_age": "64",
        "min_age": "26",
        "avg_age": "46.214285714285715"
    },
    {
        "_id": "Хихон",
        "max_age": "65",
        "min_age": "24",
        "avg_age": "46.08"
    },
    {
        "_id": "Сараево",
        "max_age": "62",
        "min_age": "28",
        "avg_age": "46.0"
    },
    {
        "_id": "Луарка",
        "max_age": "57",
        "min_age": "25",
        "avg_age": "45.75"
    },
    {
        "_id": "Гранада",
        "max_age": "61",
        "min_age": "22",
        "avg_age": "45.69230769230769"
    },
    {
        "_id": "Сеговия",
        "max_age": "65",
        "min_age": "25",
        "avg_age": "45.42857142857143"
    },
    {
        "_id": "Фигерас",
        "max_age": "62",
        "min_age": "21",
        "avg_age": "45.214285714285715"
    },
    {
        "_id": "Сан-Себастьян",
        "max_age": "63",
        "min_age": "24",
        "avg_age": "45.2"
    },
    {
        "_id": "Подгорица",
        "max_age": "64",
        "min_age": "19",
        "avg_age": "44.90909090909091"
    },
    {
        "_id": "Самора",
        "max_age": "65",
        "min_age": "21",
        "avg_age": "44.529411764705884"
    },
    {
        "_id": "Барселона",
        "max_age": "55",
        "min_age": "20",
        "avg_age": "44.142857142857146"
    },
    {
        "_id": "Рига",
        "max_age": "65",
        "min_age": "20",
        "avg_age": "43.8125"
    },
    {
        "_id": "Ташкент",
        "max_age": "65",
        "min_age": "20",
        "avg_age": "43.375"
    },
    {
        "_id": "Будапешт",
        "max_age": "55",
        "min_age": "20",
        "avg_age": "43.333333333333336"
    },
    {
        "_id": "Аликанте",
        "max_age": "64",
        "min_age": "20",
        "avg_age": "43.0"
    },
    {
        "_id": "Москва",
        "max_age": "65",
        "min_age": "20",
        "avg_age": "42.57142857142857"
    },
    {
        "_id": "Бургос",
        "max_age": "59",
        "min_age": "25",
        "avg_age": "42.54545454545455"
    },
    {
        "_id": "Осера",
        "max_age": "64",
        "min_age": "20",
        "avg_age": "42.52173913043478"
    },
    {
        "_id": "Душанбе",
        "max_age": "64",
        "min_age": "26",
        "avg_age": "42.44444444444444"
    },
    {
        "_id": "Навалькарнеро",
        "max_age": "62",
        "min_age": "18",
        "avg_age": "42.27272727272727"
    },
    {
        "_id": "Санхенхо",
        "max_age": "60",
        "min_age": "20",
        "avg_age": "42.2"
    },
    {
        "_id": "Ереван",
        "max_age": "61",
        "min_age": "20",
        "avg_age": "42.0625"
    },
    {
        "_id": "Куэнка",
        "max_age": "64",
        "min_age": "19",
        "avg_age": "42.0"
    },
    {
        "_id": "Кишинев",
        "max_age": "57",
        "min_age": "21",
        "avg_age": "41.81818181818182"
    },
    {
        "_id": "Скопье",
        "max_age": "60",
        "min_age": "22",
        "avg_age": "41.8"
    },
    {
        "_id": "Тбилиси",
        "max_age": "65",
        "min_age": "21",
        "avg_age": "41.75"
    },
    {
        "_id": "Эль-Пуэрто-де-Санта-Мария",
        "max_age": "65",
        "min_age": "26",
        "avg_age": "41.75"
    },
    {
        "_id": "Астана",
        "max_age": "64",
        "min_age": "21",
        "avg_age": "41.714285714285715"
    },
    {
        "_id": "Семана",
        "max_age": "64",
        "min_age": "18",
        "avg_age": "41.421052631578945"
    },
    {
        "_id": "Бланес",
        "max_age": "65",
        "min_age": "20",
        "avg_age": "41.333333333333336"
    },
    {
        "_id": "Санкт-Петербург",
        "max_age": "65",
        "min_age": "21",
        "avg_age": "41.27272727272727"
    },
    {
        "_id": "Мартоса",
        "max_age": "62",
        "min_age": "23",
        "avg_age": "41.1"
    },
    {
        "_id": "Монсон",
        "max_age": "63",
        "min_age": "20",
        "avg_age": "40.642857142857146"
    },
    {
        "_id": "Загреб",
        "max_age": "64",
        "min_age": "24",
        "avg_age": "40.625"
    },
    {
        "_id": "Белград",
        "max_age": "63",
        "min_age": "20",
        "avg_age": "40.583333333333336"
    },
    {
        "_id": "Тирана",
        "max_age": "65",
        "min_age": "18",
        "avg_age": "40.583333333333336"
    },
    {
        "_id": "Луго",
        "max_age": "61",
        "min_age": "20",
        "avg_age": "40.38461538461539"
    },
    {
        "_id": "Бильбао",
        "max_age": "62",
        "min_age": "21",
        "avg_age": "40.23076923076923"
    },
    {
        "_id": "Афины",
        "max_age": "61",
        "min_age": "18",
        "avg_age": "40.0"
    },
    {
        "_id": "Вильявисиоса",
        "max_age": "62",
        "min_age": "18",
        "avg_age": "39.666666666666664"
    },
    {
        "_id": "Баку",
        "max_age": "63",
        "min_age": "22",
        "avg_age": "39.6"
    },
    {
        "_id": "Бишкек",
        "max_age": "65",
        "min_age": "20",
        "avg_age": "39.57142857142857"
    },
    {
        "_id": "Артейхо",
        "max_age": "56",
        "min_age": "19",
        "avg_age": "39.44444444444444"
    },
    {
        "_id": "Любляна",
        "max_age": "60",
        "min_age": "20",
        "avg_age": "39.416666666666664"
    },
    {
        "_id": "Мурсия",
        "max_age": "64",
        "min_age": "21",
        "avg_age": "39.391304347826086"
    },
    {
        "_id": "Сория",
        "max_age": "56",
        "min_age": "18",
        "avg_age": "39.333333333333336"
    },
    {
        "_id": "Кордова",
        "max_age": "54",
        "min_age": "24",
        "avg_age": "39.2"
    },
    {
        "_id": "Овьедо",
        "max_age": "61",
        "min_age": "25",
        "avg_age": "39.18181818181818"
    },
    {
        "_id": "Хельсинки",
        "max_age": "63",
        "min_age": "19",
        "avg_age": "39.083333333333336"
    },
    {
        "_id": "Краков",
        "max_age": "56",
        "min_age": "24",
        "avg_age": "39.0"
    },
    {
        "_id": "Касерес",
        "max_age": "47",
        "min_age": "28",
        "avg_age": "39.0"
    },
    {
        "_id": "Пласенсия",
        "max_age": "59",
        "min_age": "22",
        "avg_age": "38.625"
    },
    {
        "_id": "Тарраса",
        "max_age": "64",
        "min_age": "20",
        "avg_age": "38.61538461538461"
    },
    {
        "_id": "Малага",
        "max_age": "64",
        "min_age": "19",
        "avg_age": "38.36363636363637"
    },
    {
        "_id": "Вильнюс",
        "max_age": "62",
        "min_age": "20",
        "avg_age": "38.333333333333336"
    },
    {
        "_id": "Мадрид",
        "max_age": "59",
        "min_age": "22",
        "avg_age": "38.2"
    },
    {
        "_id": "Трухильо",
        "max_age": "64",
        "min_age": "20",
        "avg_age": "37.84615384615385"
    },
    {
        "_id": "Варшава",
        "max_age": "63",
        "min_age": "19",
        "avg_age": "37.55555555555556"
    },
    {
        "_id": "Валенсия",
        "max_age": "55",
        "min_age": "20",
        "avg_age": "37.0"
    },
    {
        "_id": "Алма-Ата",
        "max_age": "56",
        "min_age": "20",
        "avg_age": "36.2"
    },
    {
        "_id": "Махадаонда",
        "max_age": "64",
        "min_age": "20",
        "avg_age": "36.142857142857146"
    },
    {
        "_id": "Лас-Росас",
        "max_age": "65",
        "min_age": "20",
        "avg_age": "36.1"
    },
    {
        "_id": "Виго",
        "max_age": "48",
        "min_age": "18",
        "avg_age": "36.0"
    },
    {
        "_id": "Мерида",
        "max_age": "60",
        "min_age": "18",
        "avg_age": "35.72222222222222"
    },
    {
        "_id": "Прага",
        "max_age": "46",
        "min_age": "21",
        "avg_age": "35.3"
    },
    {
        "_id": "Льейда",
        "max_age": "57",
        "min_age": "20",
        "avg_age": "35.1764705882353"
    },
    {
        "_id": "Вроцлав",
        "max_age": "58",
        "min_age": "19",
        "avg_age": "35.11764705882353"
    },
    {
        "_id": "Минск",
        "max_age": "50",
        "min_age": "21",
        "avg_age": "32.6"
    },
    {
        "_id": "Ла-Корунья",
        "max_age": "37",
        "min_age": "20",
        "avg_age": "31.0"
    },
    {
        "_id": "Тудела",
        "max_age": "39",
        "min_age": "20",
        "avg_age": "30.6"
    }
]